calculator/__init__.py
calculator/simpleComplexCalculator.py
simple_complex_calculator_AlixD_AdminCo-0.0.1.dist-info/METADATA
simple_complex_calculator_AlixD_AdminCo-0.0.1.dist-info/WHEEL
simple_complex_calculator_AlixD_AdminCo-0.0.1.dist-info/top_level.txt
simple_complex_calculator_AlixD_AdminCo-0.0.1.dist-info/RECORD
