Metadata-Version: 2.1
Name: simple-complex-calculator-AlixD-AdminCo
Version: 0.0.1
Summary: A calculator that can make simple operations with complexs.
Home-page: UNKNOWN
Author: Alix Deleule
Author-email: alixdeleule@cpe.fr
License: UNKNOWN
Keywords: complex calculator
Platform: UNKNOWN
